{
    "admin_view": "33c892eb-470a-4424-bdb9-08c4e9c0c7b2",
    "addfields": {
        "0": {
            "field": "64dc5d42-2334-46e7-8372-e1b5e2ac9424",
            "list": "1",
            "order_list": "1",
            "title": "1",
            "filter": "",
            "link": "1",
            "tab": "1",
            "alignment": 1,
            "order_edit": "0",
            "permission": [
                "1",
                "2",
                "3"
            ]
        }
    },
    "@dependencies": [
        {
            "key": "guid",
            "value": "33c892eb-470a-4424-bdb9-08c4e9c0c7b2",
            "entity": "admin_view",
            "table": "#__componentbuilder_admin_view",
            "direction": "out"
        },
        {
            "key": "guid",
            "value": "64dc5d42-2334-46e7-8372-e1b5e2ac9424",
            "entity": "field",
            "table": "#__componentbuilder_field",
            "direction": "out"
        }
    ]
}